odoo/addons/stock_putaway_product_template/README.rst
odoo/addons/stock_putaway_product_template/__init__.py
odoo/addons/stock_putaway_product_template/__manifest__.py
odoo/addons/stock_putaway_product_template/i18n/es.po
odoo/addons/stock_putaway_product_template/i18n/it.po
odoo/addons/stock_putaway_product_template/i18n/stock_putaway_product_template.pot
odoo/addons/stock_putaway_product_template/models/__init__.py
odoo/addons/stock_putaway_product_template/models/product.py
odoo/addons/stock_putaway_product_template/models/stock_location.py
odoo/addons/stock_putaway_product_template/models/stock_putaway_rule.py
odoo/addons/stock_putaway_product_template/readme/CONTRIBUTORS.md
odoo/addons/stock_putaway_product_template/readme/DESCRIPTION.md
odoo/addons/stock_putaway_product_template/readme/USAGE.md
odoo/addons/stock_putaway_product_template/static/description/icon.png
odoo/addons/stock_putaway_product_template/static/description/index.html
odoo/addons/stock_putaway_product_template/tests/__init__.py
odoo/addons/stock_putaway_product_template/tests/test_stock_putaway_rule.py
odoo/addons/stock_putaway_product_template/views/stock_putaway_rule_views.xml
odoo_addon_stock_putaway_product_template-18.0.1.0.1.dist-info/METADATA
odoo_addon_stock_putaway_product_template-18.0.1.0.1.dist-info/WHEEL
odoo_addon_stock_putaway_product_template-18.0.1.0.1.dist-info/top_level.txt
odoo_addon_stock_putaway_product_template-18.0.1.0.1.dist-info/RECORD
